[
  {
    "id": "intro_arbizi_welcome",
    "level": 1,
    "topic": "intro",
    "type": "phrase",
    "arabic": "أرابيزي",
    "transliteration": "Chat Arabic",
    "english": "We use numbers to represent Arabic sounds that don't exist in English.",
    "hebrew": "אנו משתמשים במספרים כדי לייצג צלילים בערבית שאינם קיימים באנגלית (או בעברית).",
    "tags": [
      "guide",
      "intro"
    ],
    "audio": "/audio/intro/intro_arbizi_welcome.mp3",
    "audio_bedouin": "/audio/intro/intro_arbizi_welcome_bedouin.mp3",
    "phonetic_arabic": "أرابيزيْ",
    "ipa_bedouin": "ʔ a r aː b iː iː",
    "gender": "female"
  },
  {
    "id": "intro_arbizi_7",
    "level": 1,
    "topic": "intro",
    "type": "phrase",
    "arabic": "ح",
    "transliteration": "7 = Ḥa",
    "english": "The number 7 represents the deep 'H' sound (like cleaning glasses).",
    "hebrew": "המספר 7 מייצג את הצליל ״ח״.",
    "tags": [
      "guide",
      "intro"
    ],
    "audio": "/audio/intro/intro_arbizi_7.mp3",
    "audio_bedouin": "/audio/intro/intro_arbizi_7_bedouin.mp3",
    "phonetic_arabic": "حْ",
    "ipa_bedouin": "ħ",
    "gender": "female"
  },
  {
    "id": "intro_arbizi_3",
    "level": 1,
    "topic": "intro",
    "type": "phrase",
    "arabic": "ع",
    "transliteration": "3 = 'Ayn",
    "english": "The number 3 represents the deep throat sound 'Ayn.",
    "hebrew": "המספר 3 מייצג את הצליל ״ע״.",
    "tags": [
      "guide",
      "intro"
    ],
    "audio": "/audio/intro/intro_arbizi_3.mp3",
    "audio_bedouin": "/audio/intro/intro_arbizi_3_bedouin.mp3",
    "phonetic_arabic": "عْ",
    "ipa_bedouin": "ʕ",
    "gender": "female"
  },
  {
    "id": "l1_g_hello",
    "level": 1,
    "topic": "greetings",
    "type": "phrase",
    "arabic": "مرحبا",
    "transliteration": "Marhaba",
    "english": "Hello",
    "hebrew": "שלום",
    "hebrewTransliteration": "מַרְחַבַּא",
    "audio": "/audio/greetings/l1_g_hello.mp3",
    "alternatives": [
      "Ahlan"
    ],
    "tags": [
      "greeting",
      "common"
    ],
    "audio_bedouin": "/audio/greetings/l1_g_hello_bedouin.mp3",
    "phonetic_arabic": "مرحباْ",
    "ipa_bedouin": "m r ħ b aː",
    "gender": "female"
  },
  {
    "id": "l1_g_howareyou_formal",
    "level": 1,
    "topic": "greetings",
    "type": "phrase",
    "arabic": "كِيف حَالَك؟",
    "transliteration": "Kif 7alak?",
    "english": "How are you? (General)",
    "hebrew": "מה שלומך? (כללי)",
    "hebrewTransliteration": "כִיף חַאלַכ?",
    "tags": [
      "greeting",
      "common"
    ],
    "audio": "/audio/greetings/l1_g_howareyou_formal.mp3",
    "audio_bedouin": "/audio/greetings/l1_g_howareyou_formal_bedouin.mp3",
    "phonetic_arabic": "كِيف حَالَك؟ْ",
    "ipa_bedouin": "k i iː f ħ a aː l a k",
    "gender": "female"
  },
  {
    "id": "l1_g_howareyou_m",
    "level": 1,
    "topic": "greetings",
    "type": "phrase",
    "arabic": "كِيفَك؟",
    "transliteration": "Kifak?",
    "english": "How are you? (to male)",
    "hebrew": "מה שלומך? (לזכר)",
    "hebrewTransliteration": "כִיפַכ?",
    "tags": [
      "greeting",
      "common"
    ],
    "gender": "female",
    "audio": "/audio/greetings/l1_g_howareyou_m.mp3",
    "audio_bedouin": "/audio/greetings/l1_g_howareyou_m_bedouin.mp3",
    "phonetic_arabic": "كِيفَك؟ْ",
    "ipa_bedouin": "k i iː f a k"
  },
  {
    "id": "l1_g_howareyou_f",
    "level": 1,
    "topic": "greetings",
    "type": "phrase",
    "arabic": "كِيفِك؟",
    "transliteration": "Kifik?",
    "english": "How are you? (to female)",
    "hebrew": "מה שלומך? (לנקבה)",
    "hebrewTransliteration": "כִיפִכ?",
    "tags": [
      "greeting",
      "common"
    ],
    "gender": "female",
    "audio": "/audio/greetings/l1_g_howareyou_f.mp3",
    "audio_bedouin": "/audio/greetings/l1_g_howareyou_f_bedouin.mp3",
    "phonetic_arabic": "كِيفِك؟ْ",
    "ipa_bedouin": "k i iː f i k"
  },
  {
    "id": "l1_g_reply_mnih",
    "level": 1,
    "topic": "greetings",
    "type": "phrase",
    "arabic": "أَنَا مْنِيح",
    "transliteration": "Ana Mni7",
    "english": "I am good (male)",
    "hebrew": "אני בסדר (זכר)",
    "hebrewTransliteration": "אַנַא מְנִיח",
    "tags": [
      "greeting",
      "reply"
    ],
    "gender": "female",
    "audio": "/audio/greetings/l1_g_reply_mnih.mp3",
    "audio_bedouin": "/audio/greetings/l1_g_reply_mnih_bedouin.mp3",
    "phonetic_arabic": "أَنَا مْنِيحْ",
    "ipa_bedouin": "ʔ a a n a aː m n i iː ħ"
  },
  {
    "id": "l1_g_reply_mniha",
    "level": 1,
    "topic": "greetings",
    "type": "phrase",
    "arabic": "أَنَا مْنِيحَة",
    "transliteration": "Ana Mni7a",
    "english": "I am good (female)",
    "hebrew": "אני בסדר (נקבה)",
    "hebrewTransliteration": "אַנַא מְנִיחַה",
    "tags": [
      "greeting",
      "reply"
    ],
    "gender": "female",
    "audio": "/audio/greetings/l1_g_reply_mniha.mp3",
    "audio_bedouin": "/audio/greetings/l1_g_reply_mniha_bedouin.mp3",
    "phonetic_arabic": "أَنَا مْنِيحَهْ",
    "ipa_bedouin": "ʔ a a n a aː m n i iː ħ a a"
  },
  {
    "id": "l1_g_reply_tamam",
    "level": 1,
    "topic": "greetings",
    "type": "phrase",
    "arabic": "تَمَام",
    "transliteration": "Tamam",
    "english": "Great / Okay / All good",
    "hebrew": "סבבה / הכל טוב",
    "hebrewTransliteration": "תַמַאם",
    "tags": [
      "greeting",
      "reply",
      "common"
    ],
    "audio": "/audio/greetings/l1_g_reply_tamam.mp3",
    "audio_bedouin": "/audio/greetings/l1_g_reply_tamam_bedouin.mp3",
    "phonetic_arabic": "تَمَامْ",
    "ipa_bedouin": "t a m a aː m",
    "gender": "female"
  },
  {
    "id": "l1_g_news",
    "level": 1,
    "topic": "greetings",
    "type": "phrase",
    "arabic": "شُو أَخْبَارَك؟",
    "transliteration": "Shu a5brak?",
    "english": "What's your news?",
    "hebrew": "מה חדש? / מה נשמע?",
    "hebrewTransliteration": "שׁוּ אַחְבַּארַכ?",
    "tags": [
      "greeting",
      "common"
    ],
    "audio": "/audio/greetings/l1_g_news.mp3",
    "audio_bedouin": "/audio/greetings/l1_g_news_bedouin.mp3",
    "phonetic_arabic": "شُو أَخْبَارَك؟ْ",
    "ipa_bedouin": "ʃ u uː ʔ a a x b a aː r a k",
    "gender": "female"
  },
  {
    "id": "l1_g_sup",
    "level": 1,
    "topic": "greetings",
    "type": "phrase",
    "arabic": "شُو فِي مَا فِي؟",
    "transliteration": "Shu fi ma fi?",
    "english": "What's up? (Literally: What is there, what is not there?)",
    "hebrew": "מה קורה? (מילולית: מה יש ומה אין?)",
    "hebrewTransliteration": "שׁוּ פִי מַא פִי?",
    "tags": [
      "greeting",
      "colloquial"
    ],
    "audio": "/audio/greetings/l1_g_sup.mp3",
    "audio_bedouin": "/audio/greetings/l1_g_sup_bedouin.mp3",
    "phonetic_arabic": "شُو فِي مَا فِي؟ْ",
    "ipa_bedouin": "ʃ u uː f i iː m a aː f i iː",
    "gender": "female"
  },
  {
    "id": "l1_g_morning",
    "level": 1,
    "topic": "greetings",
    "type": "phrase",
    "arabic": "صَبَاح الْخَيْر",
    "transliteration": "Sabah el-kheir",
    "english": "Good morning",
    "hebrew": "בוקר טוב",
    "hebrewTransliteration": "צַבַּאח אִל-חֵ'יר",
    "tags": [
      "greeting",
      "common"
    ],
    "audio": "/audio/greetings/l1_g_morning.mp3",
    "audio_bedouin": "/audio/greetings/l1_g_morning_bedouin.mp3",
    "phonetic_arabic": "صَبَاح الْخَيْرْ",
    "ipa_bedouin": "sˤ a b a aː ħ aː l x a iː r",
    "gender": "female"
  },
  {
    "id": "l1_g_welcome",
    "level": 1,
    "topic": "greetings",
    "type": "phrase",
    "arabic": "أهلاً",
    "transliteration": "Ahlan",
    "english": "Welcome / Hello",
    "hebrew": "אהלן / ברוכים הבאים",
    "hebrewTransliteration": "אַהְלָן",
    "audio": "/audio/greetings/l1_g_welcome.mp3",
    "tags": [
      "greeting"
    ],
    "audio_bedouin": "/audio/greetings/l1_g_welcome_bedouin.mp3",
    "phonetic_arabic": "أَهْلَنْْ",
    "ipa_bedouin": "ʔ a h l aː",
    "gender": "female"
  },
  {
    "id": "l1_res_thankyou",
    "level": 1,
    "topic": "essentials",
    "type": "phrase",
    "arabic": "شكراً",
    "transliteration": "Shukran",
    "english": "Thank you",
    "hebrew": "תודה",
    "hebrewTransliteration": "שׁוּכְּרַן",
    "tags": [
      "polite"
    ],
    "audio": "/audio/essentials/l1_res_thankyou.mp3",
    "audio_bedouin": "/audio/essentials/l1_res_thankyou_bedouin.mp3",
    "phonetic_arabic": "شكراًْ",
    "ipa_bedouin": "ʃ k r aː",
    "gender": "female"
  },
  {
    "id": "l1_res_yourewelcome",
    "level": 1,
    "topic": "essentials",
    "type": "phrase",
    "arabic": "عفواً",
    "transliteration": "Afwan",
    "english": "You're welcome / Excuse me",
    "hebrew": "על לא דבר / סליחה",
    "hebrewTransliteration": "עַפְוַאן",
    "tags": [
      "polite"
    ],
    "audio": "/audio/essentials/l1_res_yourewelcome.mp3",
    "audio_bedouin": "/audio/essentials/l1_res_yourewelcome_bedouin.mp3",
    "phonetic_arabic": "عفواًْ",
    "ipa_bedouin": "ʕ f uː aː",
    "gender": "female"
  },
  {
    "id": "l1_pro_i",
    "level": 1,
    "topic": "pronouns",
    "type": "word",
    "arabic": "أَنَا",
    "transliteration": "Ana",
    "english": "I",
    "hebrew": "אני",
    "hebrewTransliteration": "אַנַא",
    "tags": [
      "grammar",
      "pronoun"
    ],
    "audio": "/audio/pronouns/l1_pro_i.mp3",
    "audio_bedouin": "/audio/pronouns/l1_pro_i_bedouin.mp3",
    "phonetic_arabic": "أَنَاْ",
    "ipa_bedouin": "ʔ a a n a aː",
    "gender": "female"
  },
  {
    "id": "l1_pro_you_m",
    "level": 1,
    "topic": "pronouns",
    "type": "word",
    "arabic": "إِنْتَ",
    "transliteration": "Inte",
    "english": "You (male)",
    "hebrew": "אתה",
    "hebrewTransliteration": "אִנְתֶה",
    "tags": [
      "grammar",
      "pronoun"
    ],
    "gender": "female",
    "audio": "/audio/pronouns/l1_pro_you_m.mp3",
    "audio_bedouin": "/audio/pronouns/l1_pro_you_m_bedouin.mp3",
    "phonetic_arabic": "إِنْتَْ",
    "ipa_bedouin": "ʔ i i n t a"
  },
  {
    "id": "l1_pro_you_f",
    "level": 1,
    "topic": "pronouns",
    "type": "word",
    "arabic": "إِنْتِ",
    "transliteration": "Inti",
    "english": "You (female)",
    "hebrew": "את",
    "hebrewTransliteration": "אִנְתִי",
    "tags": [
      "grammar",
      "pronoun"
    ],
    "gender": "female",
    "audio": "/audio/pronouns/l1_pro_you_f.mp3",
    "audio_bedouin": "/audio/pronouns/l1_pro_you_f_bedouin.mp3",
    "phonetic_arabic": "إِنْتِْ",
    "ipa_bedouin": "ʔ i i n t i"
  },
  {
    "id": "l1_pro_he",
    "level": 1,
    "topic": "pronouns",
    "type": "word",
    "arabic": "هُوَّ",
    "transliteration": "Huwwe",
    "english": "He",
    "hebrew": "הוא",
    "hebrewTransliteration": "הֻוֶּה",
    "tags": [
      "grammar",
      "pronoun"
    ],
    "audio": "/audio/pronouns/l1_pro_he.mp3",
    "audio_bedouin": "/audio/pronouns/l1_pro_he_bedouin.mp3",
    "phonetic_arabic": "هُوَّْ",
    "ipa_bedouin": "h u uː ː a",
    "gender": "female"
  },
  {
    "id": "l1_pro_she",
    "level": 1,
    "topic": "pronouns",
    "type": "word",
    "arabic": "هِيَّ",
    "transliteration": "Hiyye",
    "english": "She",
    "hebrew": "היא",
    "hebrewTransliteration": "הִייֶה",
    "tags": [
      "grammar",
      "pronoun"
    ],
    "gender": "female",
    "audio": "/audio/pronouns/l1_pro_she.mp3",
    "audio_bedouin": "/audio/pronouns/l1_pro_she_bedouin.mp3",
    "phonetic_arabic": "هِيَّْ",
    "ipa_bedouin": "h i iː ː a"
  },
  {
    "id": "l1_pro_we",
    "level": 1,
    "topic": "pronouns",
    "type": "word",
    "arabic": "إِحْنَا",
    "transliteration": "Ihna",
    "english": "We",
    "hebrew": "אנחנו",
    "hebrewTransliteration": "אִחְנַא",
    "tags": [
      "grammar",
      "pronoun"
    ],
    "phonetic_arabic": "إِحْ نَاْ",
    "audio": "/audio/pronouns/l1_pro_we.mp3",
    "audio_bedouin": "/audio/pronouns/l1_pro_we_bedouin.mp3",
    "ipa_bedouin": "ʔ i i ħ n a aː",
    "gender": "female"
  },
  {
    "id": "l1_pro_you_pl",
    "level": 1,
    "topic": "pronouns",
    "type": "word",
    "arabic": "إِنْتُو",
    "transliteration": "Intu",
    "english": "You (plural)",
    "hebrew": "אתם/אתן",
    "hebrewTransliteration": "אִנְתוּ",
    "tags": [
      "grammar",
      "pronoun"
    ],
    "audio": "/audio/pronouns/l1_pro_you_pl.mp3",
    "audio_bedouin": "/audio/pronouns/l1_pro_you_pl_bedouin.mp3",
    "phonetic_arabic": "إِنْتُوْ",
    "ipa_bedouin": "ʔ i i n t u uː",
    "gender": "female"
  },
  {
    "id": "l1_pro_they",
    "level": 1,
    "topic": "pronouns",
    "type": "word",
    "arabic": "هُمَّ",
    "transliteration": "Humme",
    "english": "They",
    "hebrew": "הם/הן",
    "hebrewTransliteration": "הֻמֶּה",
    "tags": [
      "grammar",
      "pronoun"
    ],
    "audio": "/audio/pronouns/l1_pro_they.mp3",
    "audio_bedouin": "/audio/pronouns/l1_pro_they_bedouin.mp3",
    "phonetic_arabic": "هُمَّْ",
    "ipa_bedouin": "h u m ː a",
    "gender": "female"
  },
  {
    "id": "l1_g_evening",
    "level": 1,
    "topic": "greetings",
    "type": "phrase",
    "arabic": "مَسَا الْخَيْر",
    "transliteration": "Masa el-kheir",
    "english": "Good evening",
    "hebrew": "ערב טוב",
    "hebrewTransliteration": "מַסַא אִל-חֵ'יר",
    "tags": [
      "greeting",
      "common"
    ],
    "audio": "/audio/greetings/l1_g_evening.mp3",
    "audio_bedouin": "/audio/greetings/l1_g_evening_bedouin.mp3",
    "phonetic_arabic": "مَسَا الْخَيْرْ",
    "ipa_bedouin": "m a s a aː aː l x a iː r",
    "gender": "female"
  },
  {
    "id": "l1_g_goodbye",
    "level": 1,
    "topic": "greetings",
    "type": "phrase",
    "arabic": "مَع السَّلَامِة",
    "transliteration": "Ma'assalama",
    "english": "Goodbye",
    "hebrew": "להתראות",
    "hebrewTransliteration": "מַעַ אִ-סַּלַאנֶה",
    "tags": [
      "greeting",
      "common"
    ],
    "phonetic_arabic": "مَعِ السَّلَامِةْ",
    "audio": "/audio/greetings/l1_g_goodbye.mp3",
    "audio_bedouin": "/audio/greetings/l1_g_goodbye_bedouin.mp3",
    "ipa_bedouin": "m a ʕ aː l s ː a l a aː m i a",
    "gender": "female"
  },
  {
    "id": "l1_g_seeyou",
    "level": 1,
    "topic": "greetings",
    "type": "phrase",
    "arabic": "بَشُوفَك",
    "transliteration": "Bashufak",
    "english": "See you",
    "hebrew": "נתראה",
    "hebrewTransliteration": "בְּשׁוּפַכ",
    "tags": [
      "greeting",
      "common"
    ],
    "audio": "/audio/greetings/l1_g_seeyou.mp3",
    "audio_bedouin": "/audio/greetings/l1_g_seeyou_bedouin.mp3",
    "phonetic_arabic": "بَشُوفَكْ",
    "ipa_bedouin": "b a ʃ u uː f a k",
    "gender": "female"
  },
  {
    "id": "l1_basics_fast",
    "level": 1,
    "topic": "adjectives",
    "type": "word",
    "arabic": "سَرِيع",
    "transliteration": "Sari'",
    "english": "Fast",
    "hebrew": "מהיר",
    "hebrewTransliteration": "סַרִיע",
    "tags": [
      "adjective"
    ],
    "audio": "/audio/adjectives/l1_basics_fast.mp3",
    "audio_bedouin": "/audio/adjectives/l1_basics_fast_bedouin.mp3",
    "phonetic_arabic": "سَرِيعْ",
    "ipa_bedouin": "s a r i iː ʕ",
    "gender": "female"
  },
  {
    "id": "l1_basics_slow",
    "level": 1,
    "topic": "adjectives",
    "type": "word",
    "arabic": "بَطِيء",
    "transliteration": "Bati'",
    "english": "Slow",
    "hebrew": "איטי",
    "hebrewTransliteration": "בָּטִי",
    "tags": [
      "adjective"
    ],
    "phonetic_arabic": "بَطِيءْ",
    "audio": "/audio/adjectives/l1_basics_slow.mp3",
    "audio_bedouin": "/audio/adjectives/l1_basics_slow_bedouin.mp3",
    "ipa_bedouin": "b a tˤ i iː ʔ",
    "gender": "female"
  },
  {
    "id": "l1_basics_quickly",
    "level": 1,
    "topic": "adverbs",
    "type": "word",
    "arabic": "بْسُرْعَة",
    "transliteration": "B-sur'a",
    "english": "Quickly / Fast",
    "hebrew": "מהר",
    "hebrewTransliteration": "בְּסוּרְעַה",
    "tags": [
      "adverb"
    ],
    "audio": "/audio/adverbs/l1_basics_quickly.mp3",
    "audio_bedouin": "/audio/adverbs/l1_basics_quickly_bedouin.mp3",
    "phonetic_arabic": "بْسُرْعَهْ",
    "ipa_bedouin": "b s u r ʕ a a",
    "gender": "female"
  },
  {
    "id": "l1_basics_slowly",
    "level": 1,
    "topic": "adverbs",
    "type": "phrase",
    "arabic": "شْوَي شْوَي",
    "transliteration": "Shway shway",
    "english": "Slowly / Slow down",
    "hebrew": "לאט לאט",
    "hebrewTransliteration": "שְׁוַאי שְׁוַאי",
    "tags": [
      "adverb",
      "common"
    ],
    "audio": "/audio/adverbs/l1_basics_slowly.mp3",
    "audio_bedouin": "/audio/adverbs/l1_basics_slowly_bedouin.mp3",
    "phonetic_arabic": "شْوَي شْوَيْ",
    "ipa_bedouin": "ʃ w a iː ʃ w a iː",
    "gender": "female"
  },
  {
    "id": "l1_basics_kindof",
    "level": 1,
    "topic": "fillers",
    "type": "word",
    "arabic": "يَعْنِي",
    "transliteration": "Ya'ni",
    "english": "Kind of / I mean / That is",
    "hebrew": "יעני / כלומר",
    "hebrewTransliteration": "יַעְנִי",
    "tags": [
      "filler",
      "common"
    ],
    "audio": "/audio/fillers/l1_basics_kindof.mp3",
    "audio_bedouin": "/audio/fillers/l1_basics_kindof_bedouin.mp3",
    "phonetic_arabic": "يَعْنِيْ",
    "ipa_bedouin": "j a ʕ n i iː",
    "gender": "female"
  }
]