[
  {
    "id": "l2_dir_where",
    "level": 2,
    "topic": "directions",
    "type": "phrase",
    "arabic": "وِين...؟",
    "transliteration": "Wein...?",
    "english": "Where is...?",
    "tags": [
      "directions",
      "common"
    ],
    "audio": "/audio/directions/l2_dir_where.mp3"
  },
  {
    "id": "l2_dir_straight",
    "level": 2,
    "topic": "directions",
    "type": "phrase",
    "arabic": "دُغْرِي",
    "transliteration": "Dughri",
    "english": "Straight ahead",
    "tags": [
      "directions"
    ],
    "audio": "/audio/directions/l2_dir_straight.mp3"
  },
  {
    "id": "l2_dir_right",
    "level": 2,
    "topic": "directions",
    "type": "word",
    "arabic": "يَمِين",
    "transliteration": "Yamin",
    "english": "Right",
    "tags": [
      "directions"
    ],
    "audio": "/audio/directions/l2_dir_right.mp3"
  },
  {
    "id": "l2_dir_left",
    "level": 2,
    "topic": "directions",
    "type": "word",
    "arabic": "شْمَال",
    "transliteration": "Shmal",
    "english": "Left",
    "tags": [
      "directions"
    ],
    "audio": "/audio/directions/l2_dir_left.mp3"
  },
  {
    "id": "l2_dir_here",
    "level": 2,
    "topic": "directions",
    "type": "word",
    "arabic": "هُون",
    "transliteration": "Hon",
    "english": "Here",
    "tags": [
      "directions"
    ],
    "audio": "/audio/directions/l2_dir_here.mp3"
  },
  {
    "id": "l2_dir_there",
    "level": 2,
    "topic": "directions",
    "type": "word",
    "arabic": "هُنَاك",
    "transliteration": "Hunāk",
    "english": "There",
    "tags": [
      "directions"
    ],
    "audio": "/audio/directions/l2_dir_there.mp3"
  }
]